ziz_utils/__init__.py
ziz_utils/main.py
ziz_utils-6.1.0.dist-info/LICENSE
ziz_utils-6.1.0.dist-info/METADATA
ziz_utils-6.1.0.dist-info/WHEEL
ziz_utils-6.1.0.dist-info/top_level.txt
ziz_utils-6.1.0.dist-info/RECORD
